setup.py
mpSyslogHandler/__init__.py
mpSyslogHandler.egg-info/PKG-INFO
mpSyslogHandler.egg-info/SOURCES.txt
mpSyslogHandler.egg-info/dependency_links.txt
mpSyslogHandler.egg-info/top_level.txt