Metadata-Version: 1.1
Name: mpSyslogHandler
Version: 0.1.0
Summary: MultiProcess-safe SysLog Handler
Home-page: https://github.com/cmoyer/mpSysLogHandler/
Author: Chris Moyer
Author-email: cmoyer@newstex.com
License: MIT
Platform: Posix; MacOS X; Windows
Classifier: Development Status :: 3 - Alpha
Classifier: Intended Audience :: Developers
Classifier: License :: OSI Approved :: MIT License
Classifier: Operating System :: OS Independent
Classifier: Topic :: Software Development
Classifier: Programming Language :: Python :: 2
Classifier: Programming Language :: Python :: 2.5
Classifier: Programming Language :: Python :: 2.6
Classifier: Programming Language :: Python :: 2.7
